privex/__init__.py
privex/coin_handlers/KeyStore.py
privex/coin_handlers/__init__.py
privex/coin_handlers/Bitcoin/BitcoinLoader.py
privex/coin_handlers/Bitcoin/BitcoinManager.py
privex/coin_handlers/Bitcoin/BitcoinMixin.py
privex/coin_handlers/Bitcoin/__init__.py
privex/coin_handlers/Golos/GolosLoader.py
privex/coin_handlers/Golos/GolosManager.py
privex/coin_handlers/Golos/GolosMixin.py
privex/coin_handlers/Golos/__init__.py
privex/coin_handlers/Monero/MoneroLoader.py
privex/coin_handlers/Monero/MoneroManager.py
privex/coin_handlers/Monero/MoneroMixin.py
privex/coin_handlers/Monero/__init__.py
privex/coin_handlers/base/BaseHandler.py
privex/coin_handlers/base/BaseLoader.py
privex/coin_handlers/base/BaseManager.py
privex/coin_handlers/base/BatchLoader.py
privex/coin_handlers/base/SettingsMixin.py
privex/coin_handlers/base/__init__.py
privex/coin_handlers/base/decorators.py
privex/coin_handlers/base/exceptions.py
privex/coin_handlers/base/objects.py
tests/__init__.py
tests/__main__.py
tests/base.py
tests/test_bitcoin.py
tests/test_main.py
privex_coinhandlers-1.4.2.dist-info/LICENSE
privex_coinhandlers-1.4.2.dist-info/METADATA
privex_coinhandlers-1.4.2.dist-info/WHEEL
privex_coinhandlers-1.4.2.dist-info/top_level.txt
privex_coinhandlers-1.4.2.dist-info/RECORD
