Metadata-Version: 2.1
Name: privex-coinhandlers
Version: 1.4.2
Summary: Various classes for handling sending/receiving cryptocurrencies
Home-page: https://github.com/Privex/python-coinhandlers
Author: Chris (Someguy123) @ Privex
Author-email: chris@privex.io
License: MIT
Platform: UNKNOWN
Classifier: Programming Language :: Python :: 3
Classifier: Programming Language :: Python :: 3.6
Classifier: Programming Language :: Python :: 3.7
Classifier: License :: OSI Approved :: MIT License
Classifier: Operating System :: OS Independent
Requires-Dist: requests (>=2.20.1)
Requires-Dist: privex-jsonrpc (>=1.1.2)
Requires-Dist: privex-helpers (>=1.3.3)
Requires-Dist: golos-python (>=1.0.3)
Requires-Dist: python-dateutil
Requires-Dist: pytz
Requires-Dist: attrs
